asyncjob/__init__.py
asyncjob/fsm.py
asyncjob/helpers.py
asyncjob/job.py
asyncjob/py.typed
asyncjob/scheduler.py
asyncjob-0.1.2.dist-info/LICENSE
asyncjob-0.1.2.dist-info/METADATA
asyncjob-0.1.2.dist-info/WHEEL
asyncjob-0.1.2.dist-info/top_level.txt
asyncjob-0.1.2.dist-info/RECORD
