Metadata-Version: 2.1
Name: asyncjob
Version: 0.1.2
Summary: asyncjob is another simple scheduler for asyncio jobs
Home-page: https://github.com/dobryak/asyncjob
Author: Anton Dobriakov
Author-email: anton.dobryakov@gmail.com
License: GPL3
Platform: UNKNOWN
Classifier: Development Status :: 4 - Beta
Classifier: Intended Audience :: Developers
Classifier: Framework :: AsyncIO
Classifier: Programming Language :: Python :: 3.10
Classifier: License :: OSI Approved :: GNU General Public License v3 (GPLv3)
Requires-Python: >=3.10
License-File: LICENSE
